randuser/__init__.py
randuser/_modidx.py
randuser/cli.py
randuser/core.py
randuser-0.0.1.dist-info/LICENSE
randuser-0.0.1.dist-info/METADATA
randuser-0.0.1.dist-info/WHEEL
randuser-0.0.1.dist-info/entry_points.txt
randuser-0.0.1.dist-info/top_level.txt
randuser-0.0.1.dist-info/RECORD
